{
  "loss": "mse",
  "optimizer": "{'name': 'Adam', 'learning_rate': 0.001, 'decay': 0.0, 'beta_1': 0.9, 'beta_2': 0.999, 'epsilon': 1e-07, 'amsgrad': False}",
  "experiment_config": {
    "fit_args": {
      "batch_size": 64,
      "epochs": 10,
      "verbose": 2
    },
    "kfold_args": {
      "n_splits": 5,
      "shuffle": true
    },
    "path_args": {
      "repo_root": "/shared/users/geirtul/git/master/master_analysis/",
      "models": "/shared/users/geirtul/git/master/master_analysis/models/",
      "figures": "/shared/users/geirtul/git/master/master_analysis/figures/",
      "experiments": "/shared/users/geirtul/git/master/master_analysis/experiments/",
      "results": "/shared/users/geirtul/git/master/master_analysis/results",
      "model_config": "/shared/users/geirtul/git/master/master_analysis/experiments/model_config/"
    },
    "random_seed": 120,
    "data": {
      "images": "images_full_pixelmod_imbalanced.npy",
      "labels": "labels_full_pixelmod_imbalanced.npy",
      "positions": "positions_full_pixelmod_imbalanced.npy",
      "energies": "energies_full_pixelmod_imbalanced.npy"
    },
    "scaling": "minmax"
  },
  "model_type": "regression",
  "experiment_name": "generate_results_energies_single_custom",
  "experiment_id": "f42c20ae6b04",
  "datetime": "2021-01-14 16:35:07",
  "history": {
    "fold_0": {
      "loss": [
        0.001820157514885068,
        0.0015290728770196438,
        0.0014787469990551472,
        0.0014561180723831058,
        0.0014416045742109418,
        0.0014330520061776042,
        0.0014260050375014544,
        0.0014201179146766663,
        0.0014120726846158504,
        0.0014124693116173148
      ],
      "accuracy": [
        0.0,
        0.0,
        0.0,
        0.0,
        0.0,
        0.0,
        0.0,
        0.0,
        0.0,
        0.0
      ],
      "val_loss": [
        0.0018545753555372357,
        0.0016145618865266442,
        0.0018636757740750909,
        0.0017805809620767832,
        0.0019489902770146728,
        0.0014884155243635178,
        0.001500295358709991,
        0.0016811657696962357,
        0.0014812798472121358,
        0.0013390574604272842
      ],
      "val_accuracy": [
        0.0,
        0.0,
        0.0,
        0.0,
        0.0,
        0.0,
        0.0,
        0.0,
        0.0,
        0.0
      ]
    },
    "fold_1": {
      "loss": [
        0.004276592750102282,
        0.0014849086292088032,
        0.001446654205210507,
        0.001429237425327301,
        0.001420746324583888,
        0.0014111854834482074,
        0.0014071421464905143,
        0.0014006487326696515,
        0.0013949999120086432,
        0.0013956200564280152
      ],
      "accuracy": [
        0.0,
        0.0,
        0.0,
        0.0,
        0.0,
        0.0,
        0.0,
        0.0,
        0.0,
        0.0
      ],
      "val_loss": [
        0.0023091707844287157,
        0.002495052060112357,
        0.00280009675770998,
        0.002122537698596716,
        0.0018323628464713693,
        0.0018898771377280354,
        0.0017647711792960763,
        0.0019092322327196598,
        0.0017980021657422185,
        0.0019979001954197884
      ],
      "val_accuracy": [
        0.0,
        0.0,
        0.0,
        0.0,
        0.0,
        0.0,
        0.0,
        0.0,
        0.0,
        0.0
      ]
    },
    "fold_2": {
      "loss": [
        0.08692090213298798,
        0.08332765102386475,
        0.08332839608192444,
        0.08333300054073334,
        0.08333033323287964,
        0.08332749456167221,
        0.08332446962594986,
        0.08332664519548416,
        0.08332888036966324,
        0.08333020657300949
      ],
      "accuracy": [
        0.0,
        0.0,
        0.0,
        0.0,
        0.0,
        0.0,
        0.0,
        0.0,
        0.0,
        0.0
      ],
      "val_loss": [
        0.08344931155443192,
        0.08331074565649033,
        0.08328983187675476,
        0.0832679346203804,
        0.08326957374811172,
        0.08326820284128189,
        0.08326823264360428,
        0.08331664651632309,
        0.08326925337314606,
        0.08326801657676697
      ],
      "val_accuracy": [
        0.0,
        0.0,
        0.0,
        0.0,
        0.0,
        0.0,
        0.0,
        0.0,
        0.0,
        0.0
      ]
    },
    "fold_3": {
      "loss": [
        0.004506830591708422,
        0.0015188928227871656,
        0.001478452468290925,
        0.0014621661975979805,
        0.0014476666692644358,
        0.001437352504581213,
        0.001434330828487873,
        0.0014252843102440238,
        0.0014214182738214731,
        0.0014189566718414426
      ],
      "accuracy": [
        0.0,
        0.0,
        0.0,
        0.0,
        0.0,
        0.0,
        0.0,
        0.0,
        0.0,
        0.0
      ],
      "val_loss": [
        0.001454463810659945,
        0.0016796094132587314,
        0.001695009064860642,
        0.0015252885641530156,
        0.0014289307873696089,
        0.00200286996550858,
        0.0017854265170171857,
        0.0015763146802783012,
        0.0013967310078442097,
        0.0013862245250493288
      ],
      "val_accuracy": [
        0.0,
        0.0,
        0.0,
        0.0,
        0.0,
        0.0,
        0.0,
        0.0,
        0.0,
        0.0
      ]
    },
    "fold_4": {
      "loss": [
        0.00479476060718298,
        0.0014902874827384949,
        0.0014386674156412482,
        0.0014216291019693017,
        0.001410890370607376,
        0.001404222915880382,
        0.0013989127473905683,
        0.0013943823287263513,
        0.0013930212007835507,
        0.0013902921928092837
      ],
      "accuracy": [
        0.0,
        0.0,
        0.0,
        0.0,
        0.0,
        0.0,
        0.0,
        0.0,
        0.0,
        0.0
      ],
      "val_loss": [
        0.006314399186521769,
        0.006977496203035116,
        0.005702311173081398,
        0.005798189900815487,
        0.005550179164856672,
        0.004577375948429108,
        0.006520289462059736,
        0.004463589284569025,
        0.005674194544553757,
        0.0067134336568415165
      ],
      "val_accuracy": [
        0.0,
        0.0,
        0.0,
        0.0,
        0.0,
        0.0,
        0.0,
        0.0,
        0.0,
        0.0
      ]
    }
  },
  "metrics": {
    "fold_0": {
      "r2_score": 0.9839478214195917,
      "mse": 0.0013390573787355326,
      "rmse": 0.03659313294506952,
      "mae": 0.015306635781053709
    },
    "fold_1": {
      "r2_score": 0.9760271463552154,
      "mse": 0.0019978989749235778,
      "rmse": 0.044697863203106,
      "mae": 0.028114526299404557
    },
    "fold_2": {
      "r2_score": -1.1835571456231264e-07,
      "mse": 0.08326800173448812,
      "rmse": 0.28856195475926505,
      "mae": 0.24989292127319768
    },
    "fold_3": {
      "r2_score": 0.9833549714980844,
      "mse": 0.0013862257004919872,
      "rmse": 0.037232052058568936,
      "mae": 0.013029964241361927
    },
    "fold_4": {
      "r2_score": 0.9192268451592154,
      "mse": 0.0067134351394025965,
      "rmse": 0.08193555479401232,
      "mae": 0.0697009523594748
    }
  }
}